thumbor_icc/__init__.py
thumbor_icc/filters/__init__.py
thumbor_icc/filters/icc_profile_apply.py
thumbor_icc-1.1.1.dist-info/METADATA
thumbor_icc-1.1.1.dist-info/WHEEL
thumbor_icc-1.1.1.dist-info/top_level.txt
thumbor_icc-1.1.1.dist-info/RECORD
