Metadata-Version: 2.1
Name: thumbor-icc
Version: 1.1.1
Summary: Color management filters for thumbor
Home-page: https://github.com/znerol/thumbor-icc
Author: Lorenz Schori
Author-email: lo@znerol.ch
License: MIT
Keywords: thumbor,icc,images
Classifier: Development Status :: 4 - Beta
Classifier: Intended Audience :: Developers
Classifier: License :: OSI Approved :: MIT License
Classifier: Natural Language :: English
Classifier: Operating System :: POSIX :: Linux
Classifier: Programming Language :: Python :: 3.6
Classifier: Programming Language :: Python :: 3.7
Classifier: Programming Language :: Python :: 3.8
Classifier: Topic :: Multimedia :: Graphics :: Presentation
Requires-Dist: thumbor (>7.0.0.dev0)
Requires-Dist: Pillow
